llama_index/readers/file/__init__.py
llama_index/readers/file/docs/__init__.py
llama_index/readers/file/docs/base.py
llama_index/readers/file/epub/__init__.py
llama_index/readers/file/epub/base.py
llama_index/readers/file/flat/__init__.py
llama_index/readers/file/flat/base.py
llama_index/readers/file/html/__init__.py
llama_index/readers/file/html/base.py
llama_index/readers/file/image/__init__.py
llama_index/readers/file/image/base.py
llama_index/readers/file/image_caption/__init__.py
llama_index/readers/file/image_caption/base.py
llama_index/readers/file/image_deplot/README.md
llama_index/readers/file/image_deplot/__init__.py
llama_index/readers/file/image_deplot/base.py
llama_index/readers/file/image_deplot/requirements.txt
llama_index/readers/file/image_vision_llm/__init__.py
llama_index/readers/file/image_vision_llm/base.py
llama_index/readers/file/ipynb/__init__.py
llama_index/readers/file/ipynb/base.py
llama_index/readers/file/markdown/__init__.py
llama_index/readers/file/markdown/base.py
llama_index/readers/file/mbox/__init__.py
llama_index/readers/file/mbox/base.py
llama_index/readers/file/paged_csv/README.md
llama_index/readers/file/paged_csv/__init__.py
llama_index/readers/file/paged_csv/base.py
llama_index/readers/file/pymu_pdf/README.md
llama_index/readers/file/pymu_pdf/__init__.py
llama_index/readers/file/pymu_pdf/base.py
llama_index/readers/file/pymu_pdf/requirements.txt
llama_index/readers/file/rtf/README.md
llama_index/readers/file/rtf/__init__.py
llama_index/readers/file/rtf/base.py
llama_index/readers/file/slides/__init__.py
llama_index/readers/file/slides/base.py
llama_index/readers/file/slides/content_extractor.py
llama_index/readers/file/slides/image_extractor.py
llama_index/readers/file/tabular/__init__.py
llama_index/readers/file/tabular/base.py
llama_index/readers/file/unstructured/README.md
llama_index/readers/file/unstructured/__init__.py
llama_index/readers/file/unstructured/base.py
llama_index/readers/file/unstructured/requirements.txt
llama_index_readers_file-0.5.3.dist-info/METADATA
llama_index_readers_file-0.5.3.dist-info/WHEEL
llama_index_readers_file-0.5.3.dist-info/licenses/LICENSE
llama_index_readers_file-0.5.3.dist-info/RECORD
